LICENSE
MANIFEST.in
README.rst
setup.cfg
setup.py
g85_sentry_auth_oidc.egg-info/PKG-INFO
g85_sentry_auth_oidc.egg-info/SOURCES.txt
g85_sentry_auth_oidc.egg-info/dependency_links.txt
g85_sentry_auth_oidc.egg-info/entry_points.txt
g85_sentry_auth_oidc.egg-info/not-zip-safe
g85_sentry_auth_oidc.egg-info/requires.txt
g85_sentry_auth_oidc.egg-info/top_level.txt
oidc/__init__.py
oidc/apps.py
oidc/constants.py
oidc/provider.py
oidc/views.py
oidc/templates/oidc/configure.html