Metadata-Version: 1.1
Name: g85-sentry-auth-oidc
Version: 3.0.1
Summary: OpenID Connect authentication provider for Sentry
Home-page: https://www.getsentry.com
Author: Max Wittig
Author-email: max.wittig@siemens.com
License: Apache 2.0
Platform: UNKNOWN
Classifier: Intended Audience :: Developers
Classifier: Intended Audience :: System Administrators
Classifier: Operating System :: OS Independent
Classifier: Topic :: Software Development
